ldmudefunalternatives/__init__.py
ldmudefunalternatives/json.py
ldmud_efun_alternatives-0.0.1.dist-info/LICENSE
ldmud_efun_alternatives-0.0.1.dist-info/METADATA
ldmud_efun_alternatives-0.0.1.dist-info/WHEEL
ldmud_efun_alternatives-0.0.1.dist-info/entry_points.txt
ldmud_efun_alternatives-0.0.1.dist-info/top_level.txt
ldmud_efun_alternatives-0.0.1.dist-info/RECORD
