Metadata-Version: 2.1
Name: ldmud-efun-alternatives
Version: 0.0.1
Summary: Python Efun alternatives package for LDMud
Home-page: https://github.com/ldmud/python-efun-alternatives
Author: LDMud Team
Author-email: ldmud-dev@UNItopia.DE
License: UNKNOWN
Platform: UNKNOWN
Classifier: Programming Language :: Python :: 3
Classifier: License :: OSI Approved :: ISC License (ISCL)
Classifier: Operating System :: OS Independent
